cau/__init__.py
cau/cau_cli.py
cau/project/__init__.py
cau/project/project.py
cau/project/templates/cmake/module_cmakelists.txt
cau/project/templates/cmake/root_cmakelists.txt
cau/project/templates/cmake/test_cmakelists.txt
cau/project/templates/conan/conanfile.py
cau/project/templates/conan/profiles/linuxDebug
cau/project/templates/conan/profiles/linuxDefault
cau/project/templates/conan/profiles/linuxRelease
cau/project/templates/conan/profiles/win64Debug
cau/project/templates/conan/profiles/win64Default
cau/project/templates/conan/profiles/win64Release
cau/project/templates/docs/Makefile
cau/project/templates/docs/conf.py
cau/project/templates/docs/docs.yml
cau/project/templates/docs/doxygen
cau/project/templates/docs/index.md
cau/project/templates/docs/pyproject
cau/project/templates/gitlab/build.yml
cau/project/templates/gitlab/clang_format
cau/project/templates/gitlab/clang_tidy
cau/project/templates/gitlab/code_climate.yml
cau/project/templates/gitlab/gitignore
cau/project/templates/gitlab/pipeline.yml
cau/project/templates/gitlab/test.yml
cau/project/templates/header.hpp
cau/project/templates/hello/hello.cpp
cau/project/templates/hello/hello.hpp
cau/project/templates/hello/hello_test.cpp
cau/project/templates/project.toml
cau/project/templates/source.cpp
cau/project/templates/test.cpp
cau/project/templates/vscode/launch.json
cau/project/templates/vscode/settings.json
cau/project/templates/vscode/tasks.json
cau/project/tests/__init__.py
cau/project/tests/conftest.py
cau/project/tests/test_project.py
cau/tests/__init__.py
cau/tests/conftest.py
cau/tests/test_cli.py
cau/timer.py
cau/wrappers/Clang.py
cau/wrappers/Conan.py
cau/wrappers/Git.py
cau/wrappers/Valgrind.py
cau/wrappers/__init__.py
cau/wrappers/tests/__init__.py
cau/wrappers/tests/conftest.py
cau/wrappers/tests/test_Conan.py
cau/wrappers/tests/test_Coverage.py
cau/wrappers/tests/test_Git.py
cau/wrappers/tests/test_Tidy.py
cau/wrappers/tests/test_TidyMessage.py
cau/wrappers/tests/test_Valgrind.py
cpp_automation_utility-0.1.6.dist-info/LICENSE
cpp_automation_utility-0.1.6.dist-info/METADATA
cpp_automation_utility-0.1.6.dist-info/WHEEL
cpp_automation_utility-0.1.6.dist-info/entry_points.txt
cpp_automation_utility-0.1.6.dist-info/RECORD
