Metadata-Version: 2.3
Name: cpp-automation-utility
Version: 0.1.6
Summary: CLI utility to assist C++ in a devops environment
License: MIT
Author: AldridgeSoftwareDesigns
Requires-Python: >=3.10,<4.0
Classifier: License :: OSI Approved :: MIT License
Classifier: Programming Language :: Python :: 3
Classifier: Programming Language :: Python :: 3.10
Classifier: Programming Language :: Python :: 3.11
Classifier: Programming Language :: Python :: 3.12
Classifier: Programming Language :: Python :: 3.13
Requires-Dist: attrs (>=23.2.0,<24.0.0)
Requires-Dist: click (>=8.1.7,<9.0.0)
Requires-Dist: gitpython (>=3.1.43,<4.0.0)
Requires-Dist: importlib-metadata (>=8.7.0,<9.0.0)
Requires-Dist: jinja2 (>=3.1.4,<4.0.0)
Requires-Dist: lcov-cobertura (>=2.0.2,<3.0.0)
Requires-Dist: rich (>=13.7.1,<14.0.0)
Requires-Dist: tomli (>=2.0.1,<3.0.0)
